{
	"format_version": "1.20.60",
	"es_bio:dreamstone_ore": {
		"sound": "stone",
		"textures": "dreamstone_ore",
		"isotropic": true
	},
	"es_bio:gleam_ore": {
		"sound": "stone",
		"textures": "gleam_ore",
		"isotropic": true
	},
	"es_bio:mist_ore": {
		"sound": "stone",
		"textures": "mist_ore",
		"isotropic": true
	},
	"es_bio:moonstone_ore": {
		"sound": "stone",
		"textures": "moonstone_ore",
		"isotropic": true
	},
	"es_bio:slumberstone_ore": {
		"sound": "stone",
		"textures": "slumberstone_ore",
		"isotropic": true
	},
	"es_bio:dream_catcher_log": {
		"sound": "wood",
		"textures": {
			"up": "dream_catcher_log_top",
			"down": "dream_catcher_log_top",
			"north": "dream_catcher_log",
			"south": "dream_catcher_log",
			"east": "dream_catcher_log",
			"west": "dream_catcher_log"
		},
		"isotropic": true
	},
	"es_bio:dreamwood_log": {
		"sound": "wood",
		"textures": {
			"up": "dreamwood_log_top",
			"down": "dreamwood_log_top",
			"north": "dreamwood_log",
			"south": "dreamwood_log",
			"east": "dreamwood_log",
			"west": "dreamwood_log"
		},
		"isotropic": true
	},
	"es_bio:gleam_blossom_log": {
		"sound": "wood",
		"textures": {
			"up": "gleam_blossom_log_top",
			"down": "gleam_blossom_log_top",
			"north": "gleam_blossom_log",
			"south": "gleam_blossom_log",
			"east": "gleam_blossom_log",
			"west": "gleam_blossom_log"
		},
		"isotropic": true
	},
	"es_bio:mist_sycamore_log": {
		"sound": "wood",
		"textures": {
			"up": "mist_sycamore_log_top",
			"down": "mist_sycamore_log_top",
			"north": "mist_sycamore_log",
			"south": "mist_sycamore_log",
			"east": "mist_sycamore_log",
			"west": "mist_sycamore_log"
		},
		"isotropic": true
	},
	"es_bio:moonlit_willow_log": {
		"sound": "wood",
		"textures": {
			"up": "moonlit_willow_log_top",
			"down": "moonlit_willow_log_top",
			"north": "moonlit_willow_log",
			"south": "moonlit_willow_log",
			"east": "moonlit_willow_log",
			"west": "moonlit_willow_log"
		},
		"isotropic": true
	},
	"es_bio:dreamwood_plank": {
		"sound": "wood",
		"textures": "dreamwood_plank",
		"isotropic": true
	},
	"es_bio:moonlit_willow_plank": {
		"sound": "wood",
		"textures": "moonlit_willow_plank",
		"isotropic": true
	},
	"es_bio:mist_sycamore_plank": {
		"sound": "wood",
		"textures": "mist_sycamore_plank",
		"isotropic": true
	},
	"es_bio:gleam_blossom_plank": {
		"sound": "wood",
		"textures": "gleam_blossom_plank",
		"isotropic": true
	},
	"es_bio:dream_catcher_plank": {
		"sound": "wood",
		"textures": "dream_catcher_plank",
		"isotropic": true
	},
	"es_bio:dream_catcher_leaves": {
		"sound": "grass",
		"textures": "dream_catcher_leaves",
		"isotropic": true
	},
	"es_bio:dreamwood_leaves": {
		"sound": "grass",
		"textures": "dreamwood_leaves",
		"isotropic": true
	},
	"es_bio:gleam_blossom_leaves": {
		"sound": "grass",
		"textures": "gleam_blossom_leaves",
		"isotropic": true
	},
	"es_bio:mist_sycamore_leaves": {
		"sound": "grass",
		"textures": "mist_sycamore_leaves",
		"isotropic": true
	},
	"es_bio:moonlit_willow_leaves": {
		"sound": "grass",
		"textures": "moonlit_willow_leaves",
		"isotropic": true
	},
	"es_bio:dream_catcher_tree_sapling": {
		"sound": "grass",
		"textures": "dream_catcher_tree_sapling",
		"isotropic": true
	},
	"es_bio:dreamwood_tree_sapling": {
		"sound": "grass",
		"textures": "dreamwood_sapling"
	},
	"es_bio:gleam_blossom_tree_sapling": {
		"sound": "grass",
		"textures": "gleam_blossom_sapling",
		"isotropic": true
	},
	"es_bio:mist_sycamore_tree_sapling": {
		"sound": "grass",
		"textures": "mist_sycamore_sapling",
		"isotropic": true
	},
	"es_bio:moonlit_willow_tree_sapling": {
		"sound": "grass",
		"textures": "moonlit_willow_sapling",
		"isotropic": true
	},
	"es_bio:dreamstone_block": {
		"sound": "stone",
		"textures": "dreamstone_block",
		"isotropic": true
	},
	"es_bio:gleam_block": {
		"sound": "stone",
		"textures": "gleam_block",
		"isotropic": true
	},
	"es_bio:mist_block": {
		"sound": "stone",
		"textures": "mist_block",
		"isotropic": true
	},
	"es_bio:moonstone_block": {
		"sound": "stone",
		"textures": "moonstone_block",
		"isotropic": true
	},
	"es_bio:slumberstone_block": {
		"sound": "stone",
		"textures": "slumberstone_block",
		"isotropic": true
	},
	"es_bio:dream_grass_block_blue": {
		"sound": "grass",
		"textures": {
			"up": "dream_grass_block_blue_top",
			"down": "dirt",
			"north": "dream_grass_block_blue_side",
			"south": "dream_grass_block_blue_side",
			"east": "dream_grass_block_blue_side",
			"west": "dream_grass_block_blue_side"
		},
		"isotropic": false
	},
	"es_bio:dream_grass_block_pink": {
		"sound": "grass",
		"textures": {
			"up": "dream_grass_block_pink_top",
			"down": "dirt",
			"north": "dream_grass_block_pink_side",
			"south": "dream_grass_block_pink_side",
			"east": "dream_grass_block_pink_side",
			"west": "dream_grass_block_pink_side"
		},
		"isotropic": false
	},
	"es_bio:dream_grass_block_white": {
		"sound": "grass",
		"textures": {
			"up": "dream_grass_block_white_top",
			"down": "dirt",
			"north": "dream_grass_block_white_side",
			"south": "dream_grass_block_white_side",
			"east": "dream_grass_block_white_side",
			"west": "dream_grass_block_white_side"
		},
		"isotropic": false
	},
	"es_bio:dream_grass_blue_0": {
		"sound": "grass",
		"textures": "dream_grass_blue_0",
		"isotropic": {
			"down": true
		}
	},
	"es_bio:dream_grass_blue_0_tall": {
		"sound": "grass",
		"textures": "dream_grass_blue_0_tall",
		"isotropic": {
			"down": true
		}
	},
	"es_bio:dream_grass_pink_0": {
		"sound": "grass",
		"textures": "dream_grass_pink_0",
		"isotropic": {
			"down": true
		}
	},
	"es_bio:dream_grass_pink_tall_0": {
		"sound": "grass",
		"textures": "dream_grass_pink_tall_0",
		"isotropic": {
			"down": true
		}
	},
	"es_bio:dream_grass_white_0": {
		"sound": "grass",
		"textures": "dream_grass_white_0",
		"isotropic": {
			"down": true
		}
	},
	"es_bio:dream_grass_white_tall_0": {
		"sound": "grass",
		"textures": "dream_grass_white_tall_0",
		"isotropic": {
			"down": true
		}
	},
	"es_bio:dream_flower_0": {
		"sound": "grass",
		"textures": "dream_flower_0",
		"isotropic": true
	},
	"es_bio:dreamcatcher_hanging_decoration_blue": { "sound": "grass", "textures": "dreamcatcher_blue", "isotropic": true },
	"es_bio:dreamcatcher_hanging_decoration_green": { "sound": "grass", "textures": "dreamcatcher_green", "isotropic": true },
	"es_bio:dreamcatcher_hanging_decoration_lilac": { "sound": "grass", "textures": "dreamcatcher_lilac", "isotropic": true },
	"es_bio:dreamcatcher_hanging_decoration_pink": { "sound": "grass", "textures": "dreamcatcher_pink", "isotropic": true },
	"es_bio:dreamcatcher_hanging_decoration_yellow": { "sound": "grass", "textures": "dreamcatcher_yellow", "isotropic": true },
	"es_bio:dream_flower_1": {
		"sound": "grass",
		"textures": "dream_flower_1",
		"isotropic": true
	},
	"es_bio:dream_flower_2": {
		"sound": "grass",
		"textures": "dream_flower_2",
		"isotropic": true
	},
	"es_bio:dream_flower_3": {
		"sound": "grass",
		"textures": "dream_flower_3",
		"isotropic": true
	},
	"es_bio:dream_flower_4": {
		"sound": "grass",
		"textures": "dream_flower_4",
		"isotropic": true
	},
	"es_bio:gleam_blossom_flower": {
		"sound": "grass",
		"textures": "gleam_blossom_flower",
		"isotropic": true
	},
	"es_bio:blue_mushroom": {
		"sound": "grass",
		"textures": "blue_mushroom",
		"isotropic": true
	},
	"es_bio:pink_mushroom": {
		"sound": "grass",
		"textures": "pink_mushroom",
		"isotropic": true
	},
	"es_bio:white_mushroom": {
		"sound": "grass",
		"textures": "white_mushroom",
		"isotropic": true
	},
	"es_bio:dream_catcher_door": {
		"sound": "wood",
		"textures": "dream_catcher_door",
		"isotropic": true
	},
	"es_bio:dreamwood_door": {
		"sound": "wood",
		"textures": "dreamwood_door",
		"isotropic": true
	},
	"es_bio:gleam_door": {
		"sound": "wood",
		"textures": "gleam_door",
		"isotropic": true
	},
	"es_bio:mist_door": {
		"sound": "wood",
		"textures": "mist_door",
		"isotropic": true
	},
	"es_bio:moonlit_willow_door": {
		"sound": "wood",
		"textures": "moonlit_willow_door",
		"isotropic": true
	},
	"es_bio:pulsing_fluid_ore": {
		"sound": "stone",
		"textures": "pulsing_fluid_ore",
		"isotropic": true
	},
	"es_bio:veinstone_ore": {
		"sound": "stone",
		"textures": "veinstone_ore",
		"isotropic": true
	},
	"es_bio:corrupted_soil_ore": {
		"sound": "stone",
		"textures": "corrupted_soil_ore",
		"isotropic": true
	},
	"es_bio:biofilm_ore": {
		"sound": "stone",
		"textures": "biofilm_ore",
		"isotropic": true
	},
	"es_bio:incubation_husk_ore": {
		"sound": "stone",
		"textures": "incubation_husk_ore",
		"isotropic": true
	},
	"es_bio:pulsing_fluid_block": {
		"sound": "stone",
		"textures": "pulsing_fluid_block",
		"isotropic": true
	},
	"es_bio:veinstone_block": {
		"sound": "stone",
		"textures": "veinstone_block",
		"isotropic": true
	},
	"es_bio:corrupted_soil_block": {
		"sound": "stone",
		"textures": "corrupted_soil_block",
		"isotropic": true
	},
	"es_bio:biofilm_block": {
		"sound": "stone",
		"textures": "biofilm_block",
		"isotropic": true
	},
	"es_bio:incubation_husk_block": {
		"sound": "stone",
		"textures": "incubation_husk_block",
		"isotropic": true
	},

	"es_bio:spiral_log": {
		"sound": "wood",
		"textures": {
			"up": "spiral_trunk_gel_blocks",
			"down": "spiral_trunk_gel_blocks",
			"north": "spiral_trunk_black_strand",
			"south": "spiral_trunk_black_strand",
			"east": "spiral_trunk_black_strand",
			"west": "spiral_trunk_black_strand"
		},
		"isotropic": true
	},
	"es_bio:decay_bloom_log": {
		"sound": "wood",
		"textures": {
			"up": "decay_log_top",
			"down": "decay_log_top",
			"north": "decay_log",
			"south": "decay_log",
			"east": "decay_log",
			"west": "decay_log"
		},
		"isotropic": true
	},
	"es_bio:plasma_birch_log": {
		"sound": "wood",
		"textures": {
			"up": "plasma_birch_log_top",
			"down": "plasma_birch_log_top",
			"north": "plasma_birch_log",
			"south": "plasma_birch_log",
			"east": "plasma_birch_log",
			"west": "plasma_birch_log"
		},
		"isotropic": true
	},
	"es_bio:viral_resin_log": {
		"sound": "wood",
		"textures": {
			"up": "viral_resin_log_top",
			"down": "viral_resin_log_top",
			"north": "viral_resin_log",
			"south": "viral_resin_log",
			"east": "viral_resin_log",
			"west": "viral_resin_log"
		},
		"isotropic": true
	},
	"es_bio:decay_plank": {
		"sound": "wood",
		"textures": "decay_plank",
		"isotropic": true
	},
	"es_bio:plasma_birch_plank": {
		"sound": "wood",
		"textures": "plasma_birch_plank",
		"isotropic": true
	},
	"es_bio:viral_resin_plank": {
		"sound": "wood",
		"textures": "viral_resin_plank",
		"isotropic": true
	},
	"es_bio:sporecore_glass": {
		"sound": "wood",
		"textures": "sporecore_glass",
		"isotropic": true
	},
	"es_bio:sporecore_glass_cap": {
		"sound": "wood",
		"textures": "sporecore_glass_cap",
		"isotropic": true
	},
	"es_bio:sporecore_glass_fluid": {
		"sound": "grass",
		"textures": "sporecore_glass_fluid",
		"isotropic": true
	},
	"es_bio:sporecore_tendrils": {
		"sound": "grass",
		"textures": "sporecore_tendrils",
		"isotropic": true
	},
	"es_bio:spiral_energy_orb": {
		"sound": "grass",
		"textures": "spiral_energy_orb",
		"isotropic": true
	},
	"es_bio:spiral_gel_block": {
		"sound": "slime",
		"textures": "spiral_trunk_gel_blocks",
		"isotropic": true
	},
	"es_bio:decay_bloom": {
		"sound": "grass",
		"textures": "decay_bloom",
		"isotropic": true
	},
	"es_bio:plasma_nodules": {
		"sound": "grass",
		"textures": "plasma_nodules",
		"isotropic": true
	},
	"es_bio:viral_resin_leaves": {
		"sound": "grass",
		"textures": "viral_resin_leaves",
		"isotropic": true
	},
	"es_bio:viral_resin_crown": { "sound": "grass", "textures": "viral_resin_crown", "isotropic": true },
	"es_bio:viral_resin_fluid": { "sound": "grass", "textures": "viral_resin_fluid", "isotropic": true },
	"es_bio:virus_grass_block": {
		"sound": "grass",
		"textures": {
			"up": "virus_grass_block_top",
			"down": "virus_grass_block_bottom",
			"north": "virus_grass_block_side",
			"south": "virus_grass_block_side",
			"east": "virus_grass_block_side",
			"west": "virus_grass_block_side"
		},
		"isotropic": false
	},
	"es_bio:virus_spores": {
		"sound": "grass",
		"textures": "virus_spores",
		"isotropic": { "down": true }
	},
	"es_bio:virus_spore_threads": {
		"sound": "grass",
		"textures": "virus_spore_threads",
		"isotropic": { "down": true }
	},
	"es_bio:blight_bloom": {
		"sound": "grass",
		"textures": "blight_bloom",
		"isotropic": true
	},
	"es_bio:cyst_bud": {
		"sound": "grass",
		"textures": "cyst_bud",
		"isotropic": true
	},
	"es_bio:parasite_bloom": {
		"sound": "grass",
		"textures": "parasite_bloom",
		"isotropic": true
	},
	"es_bio:spore_puff": {
		"sound": "grass",
		"textures": "spore_puff",
		"isotropic": true
	},
	"es_bio:veinflower": {
		"sound": "grass",
		"textures": "veinflower",
		"isotropic": true
	},
	"es_bio:decay_door": {
		"sound": "wood",
		"textures": "decay_door",
		"isotropic": true
	},
	"es_bio:plasma_birch_door": {
		"sound": "wood",
		"textures": "plasma_birch_door",
		"isotropic": true
	},
	"es_bio:spiral_door": {
		"sound": "wood",
		"textures": "spiral_door",
		"isotropic": true
	},
	"es_bio:sporecore_door": {
		"sound": "wood",
		"textures": "sporecore_door",
		"isotropic": true
	},
	"es_bio:viral_resin_door": {
		"sound": "wood",
		"textures": "viral_resin_door",
		"isotropic": true
	},
	"es_bio:sporecore_tree_sapling": {
		"sound": "grass",
		"textures": "sporecore_sapling",
		"isotropic": true
	},
	"es_bio:spiral_tree_sapling": {
		"sound": "grass",
		"textures": "spiral_sapling",
		"isotropic": true
	},
	"es_bio:decay_bloom_tree_sapling": {
		"sound": "grass",
		"textures": "decay_bloom_sapling",
		"isotropic": true
	},
	"es_bio:plasma_birch_tree_sapling": {
		"sound": "grass",
		"textures": "plasma_birch_sapling",
		"isotropic": true
	},
	"es_bio:viral_resin_tree_sapling": {
		"sound": "grass",
		"textures": "viral_resin_sapling",
		"isotropic": true
	},
	"es_bio:ametrine_ore": { "sound": "stone", "textures": "ametrine_ore", "isotropic": true },
	"es_bio:chromite_ore": { "sound": "stone", "textures": "chromite_ore", "isotropic": true },
	"es_bio:energetic_crystal_ore": { "sound": "stone", "textures": "energetic_crystal_ore", "isotropic": true },
	"es_bio:lunaris_ore": { "sound": "stone", "textures": "lunaris_ore", "isotropic": true },
	"es_bio:primstone_ore": { "sound": "stone", "textures": "primstone_ore", "isotropic": true },
	"es_bio:ametrine_block": { "sound": "stone", "textures": "ametrine_block", "isotropic": true },
	"es_bio:chromite_block": { "sound": "stone", "textures": "chromite_block", "isotropic": true },
	"es_bio:energetic_crystal_block": { "sound": "stone", "textures": "energetic_crystal_block", "isotropic": true },
	"es_bio:lunaris_block": { "sound": "stone", "textures": "lunaris_block", "isotropic": true },
	"es_bio:primstone_block": { "sound": "stone", "textures": "primstone_block", "isotropic": true },
	"es_bio:crystal_grass_block": { "sound": "grass", "textures": "crystal_grass_block", "isotropic": true },
	"es_bio:energetic_crystal_log": { "sound": "wood", "textures": "energetic_crystal_log", "isotropic": true },
	"es_bio:ethereal_log": { "sound": "wood", "textures": "ethereal_log", "isotropic": true },
	"es_bio:moonlight_log": { "sound": "wood", "textures": "moonlight_log", "isotropic": true },
	"es_bio:prism_log": { "sound": "wood", "textures": "prism_log", "isotropic": true },
	"es_bio:quartz_log": { "sound": "wood", "textures": "quartz_log", "isotropic": true },
	"es_bio:energetic_crystal_plank": { "sound": "wood", "textures": "energetic_crystal_plank", "isotropic": true },
	"es_bio:ethereal_plank": { "sound": "wood", "textures": "ethereal_plank", "isotropic": true },
	"es_bio:moonlight_plank": { "sound": "wood", "textures": "moonlight_plank", "isotropic": true },
	"es_bio:prism_plank": { "sound": "wood", "textures": "prism_plank", "isotropic": true },
	"es_bio:energetic_crystal_leaves_blue": { "sound": "grass", "textures": "energetic_crystal_leaves_blue", "isotropic": true },
	"es_bio:energetic_crystal_leaves_green": { "sound": "grass", "textures": "energetic_crystal_leaves_green", "isotropic": true },
	"es_bio:energetic_crystal_leaves_purple": { "sound": "grass", "textures": "energetic_crystal_leaves_purple", "isotropic": true },
	"es_bio:energetic_crystal_leaves_red": { "sound": "grass", "textures": "energetic_crystal_leaves_red", "isotropic": true },
	"es_bio:ethereal_leaves": { "sound": "grass", "textures": "ethereal_leaves", "isotropic": true },
	"es_bio:ethereal_draping_leaves": { "sound": "grass", "textures": "ethereal_draping_leaves", "isotropic": true },
	"es_bio:moonlight_leaves": { "sound": "grass", "textures": "moonlight_leaves", "isotropic": true },
	"es_bio:prism_leaves_blue": { "sound": "grass", "textures": "prism_leaves_blue", "isotropic": true },
	"es_bio:prism_leaves_pink": { "sound": "grass", "textures": "prism_leaves_pink", "isotropic": true },
	"es_bio:prism_leaves_purple": { "sound": "grass", "textures": "prism_leaves_purple", "isotropic": true },
	"es_bio:prism_leaves_white": { "sound": "grass", "textures": "prism_leaves_white", "isotropic": true },
	"es_bio:quartz_leaves": { "sound": "grass", "textures": "quartz_leaves", "isotropic": true },
	"es_bio:quartz_crystal_drips": { "sound": "glass", "textures": "quartz_crystal_drips", "isotropic": true },
	"es_bio:energetic_crystal_door": { "sound": "wood", "textures": "energetic_crystal_door_lower", "isotropic": true },
	"es_bio:ethereal_door": { "sound": "wood", "textures": "ethereal_door_lower", "isotropic": true },
	"es_bio:moonlight_door": { "sound": "wood", "textures": "moonlight_door_lower", "isotropic": true },
	"es_bio:prism_door": { "sound": "wood", "textures": "prism_door_lower", "isotropic": true },
	"es_bio:quartz_door": { "sound": "wood", "textures": "quartz_door_lower", "isotropic": true },
	"es_bio:energetic_sapling": { "sound": "grass", "textures": "energetic_sapling", "isotropic": true },
	"es_bio:ethereal_sapling": { "sound": "grass", "textures": "ethereal_sapling", "isotropic": true },
	"es_bio:moonlight_sapling": { "sound": "grass", "textures": "moonlight_sapling", "isotropic": true },
	"es_bio:prism_sapling": { "sound": "grass", "textures": "prism_sapling", "isotropic": true },
	"es_bio:quartz_oak_sapling": { "sound": "grass", "textures": "quartz_oak_sapling", "isotropic": true },
	"es_bio:azure_crystal_bloom": { "sound": "grass", "textures": "azure_crystal_bloom", "isotropic": true },
	"es_bio:geode_lily": { "sound": "grass", "textures": "geode_lily", "isotropic": true },
	"es_bio:lumina_star": { "sound": "grass", "textures": "lumina_star", "isotropic": true },
	"es_bio:prism_petal": { "sound": "grass", "textures": "prism_petal", "isotropic": true },
	"es_bio:void_rose": { "sound": "grass", "textures": "void_rose", "isotropic": true },
	"es_bio:light_blue_crystal_cluster": { "sound": "glass", "textures": "light_blue_crystal_cluster", "isotropic": true },
	"es_bio:light_purple_crystal_cluster": { "sound": "glass", "textures": "light_purple_crystal_cluster", "isotropic": true },
	"es_bio:pale_pink_crystal_cluster": { "sound": "glass", "textures": "pale_pink_crystal_cluster", "isotropic": true },
	"es_bio:turquoise_crystal_cluster": { "sound": "glass", "textures": "turquoise_crystal_cluster", "isotropic": true },
	"es_bio:light_blue_crystal_spike": { "sound": "glass", "textures": "light_blue_crystal_spike", "isotropic": true },
	"es_bio:light_purple_crystal_spike": { "sound": "glass", "textures": "light_purple_crystal_spike", "isotropic": true },
	"es_bio:pale_pink_crystal_spike": { "sound": "glass", "textures": "pale_pink_crystal_spike", "isotropic": true },
	"es_bio:turquoise_crystal_spike": { "sound": "glass", "textures": "turquoise_crystal_spike", "isotropic": true }
}
